{"type": "FeatureCollection", "features": [{"properties": {"name": "石橋阪大前", "uri": "https://uedayou.net/jrslod/阪急電鉄/阪急箕面線/石橋阪大前", "railname": "阪急電鉄阪急箕面線", "door": "NULL"}, "type": "Feature", "geometry": {"type": "Point", "coordinates": [135.44615, 34.80806]}}, {"properties": {"name": "桜井", "uri": "https://uedayou.net/jrslod/阪急電鉄/阪急箕面線/桜井", "railname": "阪急電鉄阪急箕面線", "door": "NULL"}, "type": "Feature", "geometry": {"type": "Point", "coordinates": [135.4603, 34.8165]}}, {"properties": {"name": "牧落", "uri": "https://uedayou.net/jrslod/阪急電鉄/阪急箕面線/牧落", "railname": "阪急電鉄阪急箕面線", "door": "NULL"}, "type": "Feature", "geometry": {"type": "Point", "coordinates": [135.466, 34.82404]}}, {"properties": {"name": "箕面", "uri": "https://uedayou.net/jrslod/阪急電鉄/阪急箕面線/箕面", "railname": "阪急電鉄阪急箕面線", "door": "NULL"}, "type": "Feature", "geometry": {"type": "Point", "coordinates": [135.46821, 34.83436]}}]}