{"type": "FeatureCollection", "features": [{"properties": {"name": "吾野", "uri": "https://uedayou.net/jrslod/西武鉄道/西武秩父線/吾野", "railname": "西武鉄道西武秩父線", "door": "NULL"}, "type": "Feature", "geometry": {"type": "Point", "coordinates": [139.22592, 35.90829]}}, {"properties": {"name": "西吾野", "uri": "https://uedayou.net/jrslod/西武鉄道/西武秩父線/西吾野", "railname": "西武鉄道西武秩父線", "door": "NULL"}, "type": "Feature", "geometry": {"type": "Point", "coordinates": [139.20252, 35.92757]}}, {"properties": {"name": "正丸", "uri": "https://uedayou.net/jrslod/西武鉄道/西武秩父線/正丸", "railname": "西武鉄道西武秩父線", "door": "NULL"}, "type": "Feature", "geometry": {"type": "Point", "coordinates": [139.18212, 35.938]}}, {"properties": {"name": "芦ヶ久保", "uri": "https://uedayou.net/jrslod/西武鉄道/西武秩父線/芦ヶ久保", "railname": "西武鉄道西武秩父線", "door": "NULL"}, "type": "Feature", "geometry": {"type": "Point", "coordinates": [139.13702, 35.97653]}}, {"properties": {"name": "横瀬", "uri": "https://uedayou.net/jrslod/西武鉄道/西武秩父線/横瀬", "railname": "西武鉄道西武秩父線", "door": "NULL"}, "type": "Feature", "geometry": {"type": "Point", "coordinates": [139.09876, 35.98387]}}, {"properties": {"name": "西武秩父", "uri": "https://uedayou.net/jrslod/西武鉄道/西武秩父線/西武秩父", "railname": "西武鉄道西武秩父線", "door": "NULL"}, "type": "Feature", "geometry": {"type": "Point", "coordinates": [139.08262, 35.98896]}}]}