{"type": "FeatureCollection", "features": [{"properties": {"name": "あすなろう四日市", "uri": "https://uedayou.net/jrslod/四日市あすなろう鉄道/内部線/あすなろう四日市", "railname": "四日市あすなろう鉄道内部線", "door": "NULL"}, "type": "Feature", "geometry": {"type": "Point", "coordinates": [136.6185, 34.96648]}}, {"properties": {"name": "赤堀", "uri": "https://uedayou.net/jrslod/四日市あすなろう鉄道/内部線/赤堀", "railname": "四日市あすなろう鉄道内部線", "door": "NULL"}, "type": "Feature", "geometry": {"type": "Point", "coordinates": [136.61076, 34.95941]}}, {"properties": {"name": "日永", "uri": "https://uedayou.net/jrslod/四日市あすなろう鉄道/内部線/日永", "railname": "四日市あすなろう鉄道内部線", "door": "NULL"}, "type": "Feature", "geometry": {"type": "Point", "coordinates": [136.60458, 34.95623]}}, {"properties": {"name": "南日永", "uri": "https://uedayou.net/jrslod/四日市あすなろう鉄道/内部線/南日永", "railname": "四日市あすなろう鉄道内部線", "door": "NULL"}, "type": "Feature", "geometry": {"type": "Point", "coordinates": [136.60095, 34.94961]}}, {"properties": {"name": "泊", "uri": "https://uedayou.net/jrslod/四日市あすなろう鉄道/内部線/泊", "railname": "四日市あすなろう鉄道内部線", "door": "NULL"}, "type": "Feature", "geometry": {"type": "Point", "coordinates": [136.59858, 34.94074]}}, {"properties": {"name": "追分", "uri": "https://uedayou.net/jrslod/四日市あすなろう鉄道/内部線/追分", "railname": "四日市あすなろう鉄道内部線", "door": "NULL"}, "type": "Feature", "geometry": {"type": "Point", "coordinates": [136.59625, 34.93418]}}, {"properties": {"name": "小古曽", "uri": "https://uedayou.net/jrslod/四日市あすなろう鉄道/内部線/小古曽", "railname": "四日市あすなろう鉄道内部線", "door": "NULL"}, "type": "Feature", "geometry": {"type": "Point", "coordinates": [136.59246, 34.92894]}}, {"properties": {"name": "内部", "uri": "https://uedayou.net/jrslod/四日市あすなろう鉄道/内部線/内部", "railname": "四日市あすなろう鉄道内部線", "door": "NULL"}, "type": "Feature", "geometry": {"type": "Point", "coordinates": [136.58693, 34.92552]}}]}