{"type": "FeatureCollection", "features": [{"properties": {"name": "柘植", "uri": "https://uedayou.net/jrslod/西日本旅客鉄道/草津線/柘植", "railname": "西日本旅客鉄道草津線", "door": "NULL"}, "type": "Feature", "geometry": {"type": "Point", "coordinates": [136.25659, 34.84601]}}, {"properties": {"name": "油日", "uri": "https://uedayou.net/jrslod/西日本旅客鉄道/草津線/油日", "railname": "西日本旅客鉄道草津線", "door": "NULL"}, "type": "Feature", "geometry": {"type": "Point", "coordinates": [136.22904, 34.89027]}}, {"properties": {"name": "甲賀", "uri": "https://uedayou.net/jrslod/西日本旅客鉄道/草津線/甲賀", "railname": "西日本旅客鉄道草津線", "door": "NULL"}, "type": "Feature", "geometry": {"type": "Point", "coordinates": [136.2136, 34.90074]}}, {"properties": {"name": "寺庄", "uri": "https://uedayou.net/jrslod/西日本旅客鉄道/草津線/寺庄", "railname": "西日本旅客鉄道草津線", "door": "NULL"}, "type": "Feature", "geometry": {"type": "Point", "coordinates": [136.18637, 34.91875]}}, {"properties": {"name": "甲南", "uri": "https://uedayou.net/jrslod/西日本旅客鉄道/草津線/甲南", "railname": "西日本旅客鉄道草津線", "door": "NULL"}, "type": "Feature", "geometry": {"type": "Point", "coordinates": [136.1685, 34.93233]}}, {"properties": {"name": "貴生川", "uri": "https://uedayou.net/jrslod/西日本旅客鉄道/草津線/貴生川", "railname": "西日本旅客鉄道草津線", "door": "NULL"}, "type": "Feature", "geometry": {"type": "Point", "coordinates": [136.15255, 34.95264]}}, {"properties": {"name": "三雲", "uri": "https://uedayou.net/jrslod/西日本旅客鉄道/草津線/三雲", "railname": "西日本旅客鉄道草津線", "door": "NULL"}, "type": "Feature", "geometry": {"type": "Point", "coordinates": [136.1185, 34.98315]}}, {"properties": {"name": "甲西", "uri": "https://uedayou.net/jrslod/西日本旅客鉄道/草津線/甲西", "railname": "西日本旅客鉄道草津線", "door": "NULL"}, "type": "Feature", "geometry": {"type": "Point", "coordinates": [136.08127, 35.00124]}}, {"properties": {"name": "石部", "uri": "https://uedayou.net/jrslod/西日本旅客鉄道/草津線/石部", "railname": "西日本旅客鉄道草津線", "door": "NULL"}, "type": "Feature", "geometry": {"type": "Point", "coordinates": [136.05226, 35.01818]}}, {"properties": {"name": "手原", "uri": "https://uedayou.net/jrslod/西日本旅客鉄道/草津線/手原", "railname": "西日本旅客鉄道草津線", "door": "NULL"}, "type": "Feature", "geometry": {"type": "Point", "coordinates": [135.99902, 35.02741]}}, {"properties": {"name": "草津", "uri": "https://uedayou.net/jrslod/西日本旅客鉄道/草津線/草津", "railname": "西日本旅客鉄道草津線", "door": "NULL"}, "type": "Feature", "geometry": {"type": "Point", "coordinates": [135.96153, 35.02249]}}]}