{"type": "FeatureCollection", "features": [{"properties": {"name": "岡山", "uri": "https://uedayou.net/jrslod/西日本旅客鉄道/宇野線/岡山", "railname": "西日本旅客鉄道宇野線", "door": "NULL"}, "type": "Feature", "geometry": {"type": "Point", "coordinates": [133.91902, 34.66843]}}, {"properties": {"name": "大元", "uri": "https://uedayou.net/jrslod/西日本旅客鉄道/宇野線/大元", "railname": "西日本旅客鉄道宇野線", "door": "NULL"}, "type": "Feature", "geometry": {"type": "Point", "coordinates": [133.91077, 34.64769]}}, {"properties": {"name": "備前西市", "uri": "https://uedayou.net/jrslod/西日本旅客鉄道/宇野線/備前西市", "railname": "西日本旅客鉄道宇野線", "door": "NULL"}, "type": "Feature", "geometry": {"type": "Point", "coordinates": [133.89945, 34.63102]}}, {"properties": {"name": "妹尾", "uri": "https://uedayou.net/jrslod/西日本旅客鉄道/宇野線/妹尾", "railname": "西日本旅客鉄道宇野線", "door": "NULL"}, "type": "Feature", "geometry": {"type": "Point", "coordinates": [133.87235, 34.60865]}}, {"properties": {"name": "備中箕島", "uri": "https://uedayou.net/jrslod/西日本旅客鉄道/宇野線/備中箕島", "railname": "西日本旅客鉄道宇野線", "door": "NULL"}, "type": "Feature", "geometry": {"type": "Point", "coordinates": [133.85182, 34.6057]}}, {"properties": {"name": "早島", "uri": "https://uedayou.net/jrslod/西日本旅客鉄道/宇野線/早島", "railname": "西日本旅客鉄道宇野線", "door": "NULL"}, "type": "Feature", "geometry": {"type": "Point", "coordinates": [133.83445, 34.60281]}}, {"properties": {"name": "久々原", "uri": "https://uedayou.net/jrslod/西日本旅客鉄道/宇野線/久々原", "railname": "西日本旅客鉄道宇野線", "door": "NULL"}, "type": "Feature", "geometry": {"type": "Point", "coordinates": [133.82794, 34.59174]}}, {"properties": {"name": "茶屋町", "uri": "https://uedayou.net/jrslod/西日本旅客鉄道/宇野線/茶屋町", "railname": "西日本旅客鉄道宇野線", "door": "NULL"}, "type": "Feature", "geometry": {"type": "Point", "coordinates": [133.82593, 34.57818]}}, {"properties": {"name": "彦崎", "uri": "https://uedayou.net/jrslod/西日本旅客鉄道/宇野線/彦崎", "railname": "西日本旅客鉄道宇野線", "door": "NULL"}, "type": "Feature", "geometry": {"type": "Point", "coordinates": [133.83377, 34.55246]}}, {"properties": {"name": "備前片岡", "uri": "https://uedayou.net/jrslod/西日本旅客鉄道/宇野線/備前片岡", "railname": "西日本旅客鉄道宇野線", "door": "NULL"}, "type": "Feature", "geometry": {"type": "Point", "coordinates": [133.86063, 34.54463]}}, {"properties": {"name": "迫川", "uri": "https://uedayou.net/jrslod/西日本旅客鉄道/宇野線/迫川", "railname": "西日本旅客鉄道宇野線", "door": "NULL"}, "type": "Feature", "geometry": {"type": "Point", "coordinates": [133.87782, 34.53708]}}, {"properties": {"name": "常山", "uri": "https://uedayou.net/jrslod/西日本旅客鉄道/宇野線/常山", "railname": "西日本旅客鉄道宇野線", "door": "NULL"}, "type": "Feature", "geometry": {"type": "Point", "coordinates": [133.89364, 34.53117]}}, {"properties": {"name": "八浜", "uri": "https://uedayou.net/jrslod/西日本旅客鉄道/宇野線/八浜", "railname": "西日本旅客鉄道宇野線", "door": "NULL"}, "type": "Feature", "geometry": {"type": "Point", "coordinates": [133.91808, 34.53204]}}, {"properties": {"name": "備前田井", "uri": "https://uedayou.net/jrslod/西日本旅客鉄道/宇野線/備前田井", "railname": "西日本旅客鉄道宇野線", "door": "NULL"}, "type": "Feature", "geometry": {"type": "Point", "coordinates": [133.94322, 34.51595]}}, {"properties": {"name": "宇野", "uri": "https://uedayou.net/jrslod/西日本旅客鉄道/宇野線/宇野", "railname": "西日本旅客鉄道宇野線", "door": "NULL"}, "type": "Feature", "geometry": {"type": "Point", "coordinates": [133.953815, 34.495142]}}]}