{"type": "FeatureCollection", "features": [{"properties": {"name": "岡山", "uri": "https://uedayou.net/jrslod/西日本旅客鉄道/津山線/岡山", "railname": "西日本旅客鉄道津山線", "door": "NULL"}, "type": "Feature", "geometry": {"type": "Point", "coordinates": [133.91902, 34.66843]}}, {"properties": {"name": "法界院", "uri": "https://uedayou.net/jrslod/西日本旅客鉄道/津山線/法界院", "railname": "西日本旅客鉄道津山線", "door": "NULL"}, "type": "Feature", "geometry": {"type": "Point", "coordinates": [133.92705, 34.68384]}}, {"properties": {"name": "備前原", "uri": "https://uedayou.net/jrslod/西日本旅客鉄道/津山線/備前原", "railname": "西日本旅客鉄道津山線", "door": "NULL"}, "type": "Feature", "geometry": {"type": "Point", "coordinates": [133.94489, 34.70486]}}, {"properties": {"name": "玉柏", "uri": "https://uedayou.net/jrslod/西日本旅客鉄道/津山線/玉柏", "railname": "西日本旅客鉄道津山線", "door": "NULL"}, "type": "Feature", "geometry": {"type": "Point", "coordinates": [133.96377, 34.7167]}}, {"properties": {"name": "牧山", "uri": "https://uedayou.net/jrslod/西日本旅客鉄道/津山線/牧山", "railname": "西日本旅客鉄道津山線", "door": "NULL"}, "type": "Feature", "geometry": {"type": "Point", "coordinates": [133.96014, 34.74174]}}, {"properties": {"name": "野々口", "uri": "https://uedayou.net/jrslod/西日本旅客鉄道/津山線/野々口", "railname": "西日本旅客鉄道津山線", "door": "NULL"}, "type": "Feature", "geometry": {"type": "Point", "coordinates": [133.9324, 34.77141]}}, {"properties": {"name": "金川", "uri": "https://uedayou.net/jrslod/西日本旅客鉄道/津山線/金川", "railname": "西日本旅客鉄道津山線", "door": "NULL"}, "type": "Feature", "geometry": {"type": "Point", "coordinates": [133.93367, 34.7926]}}, {"properties": {"name": "建部", "uri": "https://uedayou.net/jrslod/西日本旅客鉄道/津山線/建部", "railname": "西日本旅客鉄道津山線", "door": "NULL"}, "type": "Feature", "geometry": {"type": "Point", "coordinates": [133.89897, 34.84176]}}, {"properties": {"name": "福渡", "uri": "https://uedayou.net/jrslod/西日本旅客鉄道/津山線/福渡", "railname": "西日本旅客鉄道津山線", "door": "NULL"}, "type": "Feature", "geometry": {"type": "Point", "coordinates": [133.9038, 34.87077]}}, {"properties": {"name": "神目", "uri": "https://uedayou.net/jrslod/西日本旅客鉄道/津山線/神目", "railname": "西日本旅客鉄道津山線", "door": "NULL"}, "type": "Feature", "geometry": {"type": "Point", "coordinates": [133.93557, 34.89635]}}, {"properties": {"name": "弓削", "uri": "https://uedayou.net/jrslod/西日本旅客鉄道/津山線/弓削", "railname": "西日本旅客鉄道津山線", "door": "NULL"}, "type": "Feature", "geometry": {"type": "Point", "coordinates": [133.95729, 34.92516]}}, {"properties": {"name": "誕生寺", "uri": "https://uedayou.net/jrslod/西日本旅客鉄道/津山線/誕生寺", "railname": "西日本旅客鉄道津山線", "door": "NULL"}, "type": "Feature", "geometry": {"type": "Point", "coordinates": [133.95945, 34.95117]}}, {"properties": {"name": "小原", "uri": "https://uedayou.net/jrslod/西日本旅客鉄道/津山線/小原", "railname": "西日本旅客鉄道津山線", "door": "NULL"}, "type": "Feature", "geometry": {"type": "Point", "coordinates": [133.96204, 34.96857]}}, {"properties": {"name": "亀甲", "uri": "https://uedayou.net/jrslod/西日本旅客鉄道/津山線/亀甲", "railname": "西日本旅客鉄道津山線", "door": "NULL"}, "type": "Feature", "geometry": {"type": "Point", "coordinates": [133.95878, 34.999]}}, {"properties": {"name": "佐良山", "uri": "https://uedayou.net/jrslod/西日本旅客鉄道/津山線/佐良山", "railname": "西日本旅客鉄道津山線", "door": "NULL"}, "type": "Feature", "geometry": {"type": "Point", "coordinates": [133.96088, 35.0321]}}, {"properties": {"name": "津山口", "uri": "https://uedayou.net/jrslod/西日本旅客鉄道/津山線/津山口", "railname": "西日本旅客鉄道津山線", "door": "NULL"}, "type": "Feature", "geometry": {"type": "Point", "coordinates": [133.98357, 35.05469]}}, {"properties": {"name": "津山", "uri": "https://uedayou.net/jrslod/西日本旅客鉄道/津山線/津山", "railname": "西日本旅客鉄道津山線", "door": "NULL"}, "type": "Feature", "geometry": {"type": "Point", "coordinates": [134.00244, 35.05437]}}]}