{"type": "FeatureCollection", "features": [{"properties": {"name": "日根野", "uri": "https://uedayou.net/jrslod/西日本旅客鉄道/関西空港線/日根野", "railname": "西日本旅客鉄道関西空港線", "door": "NULL"}, "type": "Feature", "geometry": {"type": "Point", "coordinates": [135.33087, 34.38997]}}, {"properties": {"name": "りんくうタウン", "uri": "https://uedayou.net/jrslod/西日本旅客鉄道/関西空港線/りんくうタウン", "railname": "西日本旅客鉄道関西空港線", "door": "NULL"}, "type": "Feature", "geometry": {"type": "Point", "coordinates": [135.29887, 34.41143]}}, {"properties": {"name": "関西空港", "uri": "https://uedayou.net/jrslod/西日本旅客鉄道/関西空港線/関西空港", "railname": "西日本旅客鉄道関西空港線", "door": "NULL"}, "type": "Feature", "geometry": {"type": "Point", "coordinates": [135.24349, 34.43597]}}]}