{"type": "FeatureCollection", "features": [{"properties": {"name": "青森", "uri": "https://uedayou.net/jrslod/東日本旅客鉄道/津軽線/青森", "railname": "東日本旅客鉄道津軽線", "door": "NULL"}, "type": "Feature", "geometry": {"type": "Point", "coordinates": [140.73407, 40.82905]}}, {"properties": {"name": "油川", "uri": "https://uedayou.net/jrslod/東日本旅客鉄道/津軽線/油川", "railname": "東日本旅客鉄道津軽線", "door": "NULL"}, "type": "Feature", "geometry": {"type": "Point", "coordinates": [140.69024, 40.85714]}}, {"properties": {"name": "津軽宮田", "uri": "https://uedayou.net/jrslod/東日本旅客鉄道/津軽線/津軽宮田", "railname": "東日本旅客鉄道津軽線", "door": "NULL"}, "type": "Feature", "geometry": {"type": "Point", "coordinates": [140.67429, 40.88753]}}, {"properties": {"name": "奥内", "uri": "https://uedayou.net/jrslod/東日本旅客鉄道/津軽線/奥内", "railname": "東日本旅客鉄道津軽線", "door": "NULL"}, "type": "Feature", "geometry": {"type": "Point", "coordinates": [140.67238, 40.90255]}}, {"properties": {"name": "左堰", "uri": "https://uedayou.net/jrslod/東日本旅客鉄道/津軽線/左堰", "railname": "東日本旅客鉄道津軽線", "door": "NULL"}, "type": "Feature", "geometry": {"type": "Point", "coordinates": [140.666, 40.91694]}}, {"properties": {"name": "後潟", "uri": "https://uedayou.net/jrslod/東日本旅客鉄道/津軽線/後潟", "railname": "東日本旅客鉄道津軽線", "door": "NULL"}, "type": "Feature", "geometry": {"type": "Point", "coordinates": [140.66267, 40.93094]}}, {"properties": {"name": "中沢", "uri": "https://uedayou.net/jrslod/東日本旅客鉄道/津軽線/中沢", "railname": "東日本旅客鉄道津軽線", "door": "NULL"}, "type": "Feature", "geometry": {"type": "Point", "coordinates": [140.65609, 40.9494]}}, {"properties": {"name": "蓬田", "uri": "https://uedayou.net/jrslod/東日本旅客鉄道/津軽線/蓬田", "railname": "東日本旅客鉄道津軽線", "door": "NULL"}, "type": "Feature", "geometry": {"type": "Point", "coordinates": [140.65451, 40.9696]}}, {"properties": {"name": "郷沢", "uri": "https://uedayou.net/jrslod/東日本旅客鉄道/津軽線/郷沢", "railname": "東日本旅客鉄道津軽線", "door": "NULL"}, "type": "Feature", "geometry": {"type": "Point", "coordinates": [140.65251, 40.98736]}}, {"properties": {"name": "瀬辺地", "uri": "https://uedayou.net/jrslod/東日本旅客鉄道/津軽線/瀬辺地", "railname": "東日本旅客鉄道津軽線", "door": "NULL"}, "type": "Feature", "geometry": {"type": "Point", "coordinates": [140.64807, 41.00813]}}, {"properties": {"name": "蟹田", "uri": "https://uedayou.net/jrslod/東日本旅客鉄道/津軽線/蟹田", "railname": "東日本旅客鉄道津軽線", "door": "NULL"}, "type": "Feature", "geometry": {"type": "Point", "coordinates": [140.64288, 41.03798]}}, {"properties": {"name": "中小国", "uri": "https://uedayou.net/jrslod/東日本旅客鉄道/津軽線/中小国", "railname": "東日本旅客鉄道津軽線", "door": "NULL"}, "type": "Feature", "geometry": {"type": "Point", "coordinates": [140.59738, 41.05138]}}, {"properties": {"name": "大平", "uri": "https://uedayou.net/jrslod/東日本旅客鉄道/津軽線/大平", "railname": "東日本旅客鉄道津軽線", "door": "NULL"}, "type": "Feature", "geometry": {"type": "Point", "coordinates": [140.56013, 41.06586]}}, {"properties": {"name": "津軽二股", "uri": "https://uedayou.net/jrslod/東日本旅客鉄道/津軽線/津軽二股", "railname": "東日本旅客鉄道津軽線", "door": "NULL"}, "type": "Feature", "geometry": {"type": "Point", "coordinates": [140.51458, 41.14551]}}, {"properties": {"name": "大川平", "uri": "https://uedayou.net/jrslod/東日本旅客鉄道/津軽線/大川平", "railname": "東日本旅客鉄道津軽線", "door": "NULL"}, "type": "Feature", "geometry": {"type": "Point", "coordinates": [140.50761, 41.16351]}}, {"properties": {"name": "今別", "uri": "https://uedayou.net/jrslod/東日本旅客鉄道/津軽線/今別", "railname": "東日本旅客鉄道津軽線", "door": "NULL"}, "type": "Feature", "geometry": {"type": "Point", "coordinates": [140.49009, 41.18006]}}, {"properties": {"name": "津軽浜名", "uri": "https://uedayou.net/jrslod/東日本旅客鉄道/津軽線/津軽浜名", "railname": "東日本旅客鉄道津軽線", "door": "NULL"}, "type": "Feature", "geometry": {"type": "Point", "coordinates": [140.47254, 41.18051]}}, {"properties": {"name": "三厩", "uri": "https://uedayou.net/jrslod/東日本旅客鉄道/津軽線/三厩", "railname": "東日本旅客鉄道津軽線", "door": "NULL"}, "type": "Feature", "geometry": {"type": "Point", "coordinates": [140.44487, 41.18575]}}]}