{"type": "FeatureCollection", "features": [{"properties": {"name": "池袋", "uri": "https://uedayou.net/jrslod/東日本旅客鉄道/赤羽線/池袋", "railname": "東日本旅客鉄道赤羽線", "door": "NULL"}, "type": "Feature", "geometry": {"type": "Point", "coordinates": [139.71071, 35.72896]}}, {"properties": {"name": "板橋", "uri": "https://uedayou.net/jrslod/東日本旅客鉄道/赤羽線/板橋", "railname": "東日本旅客鉄道赤羽線", "door": "NULL"}, "type": "Feature", "geometry": {"type": "Point", "coordinates": [139.71924, 35.7451]}}, {"properties": {"name": "十条", "uri": "https://uedayou.net/jrslod/東日本旅客鉄道/赤羽線/十条", "railname": "東日本旅客鉄道赤羽線", "door": "NULL"}, "type": "Feature", "geometry": {"type": "Point", "coordinates": [139.72225, 35.75961]}}, {"properties": {"name": "赤羽", "uri": "https://uedayou.net/jrslod/東日本旅客鉄道/赤羽線/赤羽", "railname": "東日本旅客鉄道赤羽線", "door": "NULL"}, "type": "Feature", "geometry": {"type": "Point", "coordinates": [139.72097, 35.77755]}}]}