{"type": "FeatureCollection", "features": [{"properties": {"name": "函館駅前", "uri": "https://uedayou.net/jrslod/函館市企業局交通部/大森線/函館駅前", "railname": "函館市企業局交通部大森線", "door": "NULL"}, "type": "Feature", "geometry": {"type": "Point", "coordinates": [140.72785, 41.77213]}}, {"properties": {"name": "松風町", "uri": "https://uedayou.net/jrslod/函館市企業局交通部/大森線/松風町", "railname": "函館市企業局交通部大森線", "door": "NULL"}, "type": "Feature", "geometry": {"type": "Point", "coordinates": [140.73312, 41.7712]}}]}