{"type": "FeatureCollection", "features": [{"properties": {"name": "京成成田", "uri": "https://uedayou.net/jrslod/京成電鉄/京成東成田線/京成成田", "railname": "京成電鉄京成東成田線", "door": "NULL"}, "type": "Feature", "geometry": {"type": "Point", "coordinates": [140.31612, 35.77671]}}, {"properties": {"name": "東成田", "uri": "https://uedayou.net/jrslod/京成電鉄/京成東成田線/東成田", "railname": "京成電鉄京成東成田線", "door": "NULL"}, "type": "Feature", "geometry": {"type": "Point", "coordinates": [140.38676, 35.77035]}}]}