{"type": "FeatureCollection", "features": [{"properties": {"name": "川西", "uri": "https://uedayou.net/jrslod/錦川鉄道/錦川清流線/川西", "railname": "錦川鉄道錦川清流線", "door": "NULL"}, "type": "Feature", "geometry": {"type": "Point", "coordinates": [132.17702, 34.15615]}}, {"properties": {"name": "清流新岩国", "uri": "https://uedayou.net/jrslod/錦川鉄道/錦川清流線/清流新岩国", "railname": "錦川鉄道錦川清流線", "door": "NULL"}, "type": "Feature", "geometry": {"type": "Point", "coordinates": [132.14751, 34.16282]}}, {"properties": {"name": "守内かさ神", "uri": "https://uedayou.net/jrslod/錦川鉄道/錦川清流線/守内かさ神", "railname": "錦川鉄道錦川清流線", "door": "NULL"}, "type": "Feature", "geometry": {"type": "Point", "coordinates": [132.13564, 34.17014]}}, {"properties": {"name": "南河内", "uri": "https://uedayou.net/jrslod/錦川鉄道/錦川清流線/南河内", "railname": "錦川鉄道錦川清流線", "door": "NULL"}, "type": "Feature", "geometry": {"type": "Point", "coordinates": [132.10368, 34.16618]}}, {"properties": {"name": "行波", "uri": "https://uedayou.net/jrslod/錦川鉄道/錦川清流線/行波", "railname": "錦川鉄道錦川清流線", "door": "NULL"}, "type": "Feature", "geometry": {"type": "Point", "coordinates": [132.0873, 34.16302]}}, {"properties": {"name": "北河内", "uri": "https://uedayou.net/jrslod/錦川鉄道/錦川清流線/北河内", "railname": "錦川鉄道錦川清流線", "door": "NULL"}, "type": "Feature", "geometry": {"type": "Point", "coordinates": [132.06495, 34.17581]}}, {"properties": {"name": "椋野", "uri": "https://uedayou.net/jrslod/錦川鉄道/錦川清流線/椋野", "railname": "錦川鉄道錦川清流線", "door": "NULL"}, "type": "Feature", "geometry": {"type": "Point", "coordinates": [132.03347, 34.194]}}, {"properties": {"name": "南桑", "uri": "https://uedayou.net/jrslod/錦川鉄道/錦川清流線/南桑", "railname": "錦川鉄道錦川清流線", "door": "NULL"}, "type": "Feature", "geometry": {"type": "Point", "coordinates": [132.02135, 34.20918]}}, {"properties": {"name": "清流みはらし", "uri": "https://uedayou.net/jrslod/錦川鉄道/錦川清流線/清流みはらし", "railname": "錦川鉄道錦川清流線", "door": "NULL"}, "type": "Feature", "geometry": {"type": "Point", "coordinates": [132.00627, 34.21101]}}, {"properties": {"name": "根笠", "uri": "https://uedayou.net/jrslod/錦川鉄道/錦川清流線/根笠", "railname": "錦川鉄道錦川清流線", "door": "NULL"}, "type": "Feature", "geometry": {"type": "Point", "coordinates": [131.99882, 34.21081]}}, {"properties": {"name": "河山", "uri": "https://uedayou.net/jrslod/錦川鉄道/錦川清流線/河山", "railname": "錦川鉄道錦川清流線", "door": "NULL"}, "type": "Feature", "geometry": {"type": "Point", "coordinates": [131.98427, 34.23645]}}, {"properties": {"name": "柳瀬", "uri": "https://uedayou.net/jrslod/錦川鉄道/錦川清流線/柳瀬", "railname": "錦川鉄道錦川清流線", "door": "NULL"}, "type": "Feature", "geometry": {"type": "Point", "coordinates": [131.97672, 34.25705]}}, {"properties": {"name": "錦町", "uri": "https://uedayou.net/jrslod/錦川鉄道/錦川清流線/錦町", "railname": "錦川鉄道錦川清流線", "door": "NULL"}, "type": "Feature", "geometry": {"type": "Point", "coordinates": [131.96341, 34.26466]}}]}