{"type": "FeatureCollection", "features": [{"properties": {"name": "那覇空港", "uri": "https://uedayou.net/jrslod/沖縄都市モノレール/沖縄都市モノレール線/那覇空港", "railname": "沖縄都市モノレール沖縄都市モノレール線", "door": "2003/08/01 00:00"}, "type": "Feature", "geometry": {"type": "Point", "coordinates": [127.65229, 26.20636]}}, {"properties": {"name": "赤嶺", "uri": "https://uedayou.net/jrslod/沖縄都市モノレール/沖縄都市モノレール線/赤嶺", "railname": "沖縄都市モノレール沖縄都市モノレール線", "door": "2003/08/01 00:00"}, "type": "Feature", "geometry": {"type": "Point", "coordinates": [127.66031, 26.19319]}}, {"properties": {"name": "小禄", "uri": "https://uedayou.net/jrslod/沖縄都市モノレール/沖縄都市モノレール線/小禄", "railname": "沖縄都市モノレール沖縄都市モノレール線", "door": "2003/08/01 00:00"}, "type": "Feature", "geometry": {"type": "Point", "coordinates": [127.66727, 26.19675]}}, {"properties": {"name": "奥武山公園", "uri": "https://uedayou.net/jrslod/沖縄都市モノレール/沖縄都市モノレール線/奥武山公園", "railname": "沖縄都市モノレール沖縄都市モノレール線", "door": "2003/08/01 00:00"}, "type": "Feature", "geometry": {"type": "Point", "coordinates": [127.67494, 26.20054]}}, {"properties": {"name": "壺川", "uri": "https://uedayou.net/jrslod/沖縄都市モノレール/沖縄都市モノレール線/壺川", "railname": "沖縄都市モノレール沖縄都市モノレール線", "door": "2003/08/01 00:00"}, "type": "Feature", "geometry": {"type": "Point", "coordinates": [127.67821, 26.2061]}}, {"properties": {"name": "旭橋", "uri": "https://uedayou.net/jrslod/沖縄都市モノレール/沖縄都市モノレール線/旭橋", "railname": "沖縄都市モノレール沖縄都市モノレール線", "door": "2003/08/01 00:00"}, "type": "Feature", "geometry": {"type": "Point", "coordinates": [127.6754, 26.21162]}}, {"properties": {"name": "県庁前", "uri": "https://uedayou.net/jrslod/沖縄都市モノレール/沖縄都市モノレール線/県庁前", "railname": "沖縄都市モノレール沖縄都市モノレール線", "door": "2003/08/01 00:00"}, "type": "Feature", "geometry": {"type": "Point", "coordinates": [127.67948, 26.21454]}}, {"properties": {"name": "美栄橋", "uri": "https://uedayou.net/jrslod/沖縄都市モノレール/沖縄都市モノレール線/美栄橋", "railname": "沖縄都市モノレール沖縄都市モノレール線", "door": "2003/08/01 00:00"}, "type": "Feature", "geometry": {"type": "Point", "coordinates": [127.68465, 26.21927]}}, {"properties": {"name": "牧志", "uri": "https://uedayou.net/jrslod/沖縄都市モノレール/沖縄都市モノレール線/牧志", "railname": "沖縄都市モノレール沖縄都市モノレール線", "door": "2003/08/01 00:00"}, "type": "Feature", "geometry": {"type": "Point", "coordinates": [127.69266, 26.21693]}}, {"properties": {"name": "安里", "uri": "https://uedayou.net/jrslod/沖縄都市モノレール/沖縄都市モノレール線/安里", "railname": "沖縄都市モノレール沖縄都市モノレール線", "door": "2003/08/01 00:00"}, "type": "Feature", "geometry": {"type": "Point", "coordinates": [127.69587, 26.217]}}, {"properties": {"name": "おもろまち", "uri": "https://uedayou.net/jrslod/沖縄都市モノレール/沖縄都市モノレール線/おもろまち", "railname": "沖縄都市モノレール沖縄都市モノレール線", "door": "2003/08/01 00:00"}, "type": "Feature", "geometry": {"type": "Point", "coordinates": [127.69848, 26.22243]}}, {"properties": {"name": "古島", "uri": "https://uedayou.net/jrslod/沖縄都市モノレール/沖縄都市モノレール線/古島", "railname": "沖縄都市モノレール沖縄都市モノレール線", "door": "2003/08/01 00:00"}, "type": "Feature", "geometry": {"type": "Point", "coordinates": [127.70279, 26.23035]}}, {"properties": {"name": "市立病院前", "uri": "https://uedayou.net/jrslod/沖縄都市モノレール/沖縄都市モノレール線/市立病院前", "railname": "沖縄都市モノレール沖縄都市モノレール線", "door": "2003/08/01 00:00"}, "type": "Feature", "geometry": {"type": "Point", "coordinates": [127.71052, 26.22715]}}, {"properties": {"name": "儀保", "uri": "https://uedayou.net/jrslod/沖縄都市モノレール/沖縄都市モノレール線/儀保", "railname": "沖縄都市モノレール沖縄都市モノレール線", "door": "2003/08/01 00:00"}, "type": "Feature", "geometry": {"type": "Point", "coordinates": [127.7196, 26.22422]}}, {"properties": {"name": "首里", "uri": "https://uedayou.net/jrslod/沖縄都市モノレール/沖縄都市モノレール線/首里", "railname": "沖縄都市モノレール沖縄都市モノレール線", "door": "2003/08/01 00:00"}, "type": "Feature", "geometry": {"type": "Point", "coordinates": [127.725185, 26.218986]}}, {"properties": {"name": "石嶺", "uri": "https://uedayou.net/jrslod/沖縄都市モノレール/沖縄都市モノレール線/石嶺", "railname": "沖縄都市モノレール沖縄都市モノレール線", "door": "2019/10/01 00:00"}, "type": "Feature", "geometry": {"type": "Point", "coordinates": [127.729156, 26.227344]}}, {"properties": {"name": "経塚", "uri": "https://uedayou.net/jrslod/沖縄都市モノレール/沖縄都市モノレール線/経塚", "railname": "沖縄都市モノレール沖縄都市モノレール線", "door": "2019/10/01 00:00"}, "type": "Feature", "geometry": {"type": "Point", "coordinates": [127.728177, 26.236503]}}, {"properties": {"name": "浦添前田", "uri": "https://uedayou.net/jrslod/沖縄都市モノレール/沖縄都市モノレール線/浦添前田", "railname": "沖縄都市モノレール沖縄都市モノレール線", "door": "2019/10/01 00:00"}, "type": "Feature", "geometry": {"type": "Point", "coordinates": [127.731895, 26.243961]}}, {"properties": {"name": "てだこ浦西", "uri": "https://uedayou.net/jrslod/沖縄都市モノレール/沖縄都市モノレール線/てだこ浦西", "railname": "沖縄都市モノレール沖縄都市モノレール線", "door": "2019/10/01 00:00"}, "type": "Feature", "geometry": {"type": "Point", "coordinates": [127.742289, 26.241609]}}]}