{"type": "FeatureCollection", "features": [{"properties": {"name": "姪浜", "uri": "https://uedayou.net/jrslod/福岡市交通局/空港線/姪浜", "railname": "福岡市交通局空港線", "door": "2004/03/01 00:00"}, "type": "Feature", "geometry": {"type": "Point", "coordinates": [130.32417, 33.58363]}}, {"properties": {"name": "室見", "uri": "https://uedayou.net/jrslod/福岡市交通局/空港線/室見", "railname": "福岡市交通局空港線", "door": "2004/03/01 00:00"}, "type": "Feature", "geometry": {"type": "Point", "coordinates": [130.33947, 33.58074]}}, {"properties": {"name": "藤崎", "uri": "https://uedayou.net/jrslod/福岡市交通局/空港線/藤崎", "railname": "福岡市交通局空港線", "door": "2004/03/01 00:00"}, "type": "Feature", "geometry": {"type": "Point", "coordinates": [130.34831, 33.58135]}}, {"properties": {"name": "西新", "uri": "https://uedayou.net/jrslod/福岡市交通局/空港線/西新", "railname": "福岡市交通局空港線", "door": "2004/03/01 00:00"}, "type": "Feature", "geometry": {"type": "Point", "coordinates": [130.3598, 33.58391]}}, {"properties": {"name": "唐人町", "uri": "https://uedayou.net/jrslod/福岡市交通局/空港線/唐人町", "railname": "福岡市交通局空港線", "door": "2004/03/01 00:00"}, "type": "Feature", "geometry": {"type": "Point", "coordinates": [130.36994, 33.5901]}}, {"properties": {"name": "大濠公園", "uri": "https://uedayou.net/jrslod/福岡市交通局/空港線/大濠公園", "railname": "福岡市交通局空港線", "door": "2004/03/01 00:00"}, "type": "Feature", "geometry": {"type": "Point", "coordinates": [130.37918, 33.59005]}}, {"properties": {"name": "赤坂", "uri": "https://uedayou.net/jrslod/福岡市交通局/空港線/赤坂", "railname": "福岡市交通局空港線", "door": "2004/03/01 00:00"}, "type": "Feature", "geometry": {"type": "Point", "coordinates": [130.39015, 33.58895]}}, {"properties": {"name": "天神", "uri": "https://uedayou.net/jrslod/福岡市交通局/空港線/天神", "railname": "福岡市交通局空港線", "door": "2004/03/01 00:00"}, "type": "Feature", "geometry": {"type": "Point", "coordinates": [130.39924, 33.59139]}}, {"properties": {"name": "中洲川端", "uri": "https://uedayou.net/jrslod/福岡市交通局/空港線/中洲川端", "railname": "福岡市交通局空港線", "door": "2004/03/01 00:00"}, "type": "Feature", "geometry": {"type": "Point", "coordinates": [130.40595, 33.59422]}}, {"properties": {"name": "祗園", "uri": "https://uedayou.net/jrslod/福岡市交通局/空港線/祗園", "railname": "福岡市交通局空港線", "door": "NULL"}, "type": "Feature", "geometry": {"type": "Point", "coordinates": [130.41401, 33.59435]}}, {"properties": {"name": "博多", "uri": "https://uedayou.net/jrslod/福岡市交通局/空港線/博多", "railname": "福岡市交通局空港線", "door": "2004/03/01 00:00"}, "type": "Feature", "geometry": {"type": "Point", "coordinates": [130.42131, 33.59005]}}, {"properties": {"name": "東比恵", "uri": "https://uedayou.net/jrslod/福岡市交通局/空港線/東比恵", "railname": "福岡市交通局空港線", "door": "2004/03/01 00:00"}, "type": "Feature", "geometry": {"type": "Point", "coordinates": [130.43102, 33.58936]}}, {"properties": {"name": "福岡空港", "uri": "https://uedayou.net/jrslod/福岡市交通局/空港線/福岡空港", "railname": "福岡市交通局空港線", "door": "2004/03/01 00:00"}, "type": "Feature", "geometry": {"type": "Point", "coordinates": [130.44739, 33.59753]}}]}