{"type": "FeatureCollection", "features": [{"properties": {"name": "住吉", "uri": "https://uedayou.net/jrslod/長崎電気軌道/赤迫支線/住吉", "railname": "長崎電気軌道赤迫支線", "door": "NULL"}, "type": "Feature", "geometry": {"type": "Point", "coordinates": [129.85974, 32.7922]}}, {"properties": {"name": "赤迫", "uri": "https://uedayou.net/jrslod/長崎電気軌道/赤迫支線/赤迫", "railname": "長崎電気軌道赤迫支線", "door": "NULL"}, "type": "Feature", "geometry": {"type": "Point", "coordinates": [129.85762, 32.79389]}}]}