{"type": "FeatureCollection", "features": [{"properties": {"name": "横山", "uri": "https://uedayou.net/jrslod/神戸電鉄/公園都市線/横山", "railname": "神戸電鉄公園都市線", "door": "NULL"}, "type": "Feature", "geometry": {"type": "Point", "coordinates": [135.21972, 34.87664]}}, {"properties": {"name": "フラワータウン", "uri": "https://uedayou.net/jrslod/神戸電鉄/公園都市線/フラワータウン", "railname": "神戸電鉄公園都市線", "door": "NULL"}, "type": "Feature", "geometry": {"type": "Point", "coordinates": [135.20255, 34.88536]}}, {"properties": {"name": "南ウッディタウン", "uri": "https://uedayou.net/jrslod/神戸電鉄/公園都市線/南ウッディタウン", "railname": "神戸電鉄公園都市線", "door": "NULL"}, "type": "Feature", "geometry": {"type": "Point", "coordinates": [135.18997, 34.90136]}}, {"properties": {"name": "ウッディタウン中央", "uri": "https://uedayou.net/jrslod/神戸電鉄/公園都市線/ウッディタウン中央", "railname": "神戸電鉄公園都市線", "door": "NULL"}, "type": "Feature", "geometry": {"type": "Point", "coordinates": [135.18353, 34.91006]}}]}