{"type": "FeatureCollection", "features": [{"properties": {"name": "東成田", "uri": "https://uedayou.net/jrslod/芝山鉄道/芝山鉄道線/東成田", "railname": "芝山鉄道芝山鉄道線", "door": "NULL"}, "type": "Feature", "geometry": {"type": "Point", "coordinates": [140.38676, 35.77035]}}, {"properties": {"name": "芝山千代田", "uri": "https://uedayou.net/jrslod/芝山鉄道/芝山鉄道線/芝山千代田", "railname": "芝山鉄道芝山鉄道線", "door": "NULL"}, "type": "Feature", "geometry": {"type": "Point", "coordinates": [140.39895, 35.75429]}}]}