{"type": "FeatureCollection", "features": [{"properties": {"name": "道明寺", "uri": "https://uedayou.net/jrslod/近畿日本鉄道/近鉄道明寺線/道明寺", "railname": "近畿日本鉄道近鉄道明寺線", "door": "NULL"}, "type": "Feature", "geometry": {"type": "Point", "coordinates": [135.62035, 34.56909]}}, {"properties": {"name": "柏原南口", "uri": "https://uedayou.net/jrslod/近畿日本鉄道/近鉄道明寺線/柏原南口", "railname": "近畿日本鉄道近鉄道明寺線", "door": "NULL"}, "type": "Feature", "geometry": {"type": "Point", "coordinates": [135.62502, 34.58197]}}, {"properties": {"name": "柏原", "uri": "https://uedayou.net/jrslod/近畿日本鉄道/近鉄道明寺線/柏原", "railname": "近畿日本鉄道近鉄道明寺線", "door": "NULL"}, "type": "Feature", "geometry": {"type": "Point", "coordinates": [135.62324, 34.5866]}}]}