{"type": "FeatureCollection", "features": [{"properties": {"name": "名取", "uri": "https://uedayou.net/jrslod/仙台空港鉄道/仙台空港線/名取", "railname": "仙台空港鉄道仙台空港線", "door": "NULL"}, "type": "Feature", "geometry": {"type": "Point", "coordinates": [140.88269, 38.17419]}}, {"properties": {"name": "杜せきのした", "uri": "https://uedayou.net/jrslod/仙台空港鉄道/仙台空港線/杜せきのした", "railname": "仙台空港鉄道仙台空港線", "door": "NULL"}, "type": "Feature", "geometry": {"type": "Point", "coordinates": [140.89635, 38.1653]}}, {"properties": {"name": "美田園", "uri": "https://uedayou.net/jrslod/仙台空港鉄道/仙台空港線/美田園", "railname": "仙台空港鉄道仙台空港線", "door": "NULL"}, "type": "Feature", "geometry": {"type": "Point", "coordinates": [140.91703, 38.1598]}}, {"properties": {"name": "仙台空港", "uri": "https://uedayou.net/jrslod/仙台空港鉄道/仙台空港線/仙台空港", "railname": "仙台空港鉄道仙台空港線", "door": "NULL"}, "type": "Feature", "geometry": {"type": "Point", "coordinates": [140.92887, 38.13719]}}]}