{"type": "FeatureCollection", "features": [{"properties": {"name": "山麓駅", "uri": "https://uedayou.net/jrslod/皿倉登山鉄道/皿倉山ケーブルカー/山麓駅", "railname": "皿倉登山鉄道皿倉山ケーブルカー", "door": "NULL"}, "type": "Feature", "geometry": {"type": "Point", "coordinates": [130.79646, 33.85678]}}, {"properties": {"name": "山上駅", "uri": "https://uedayou.net/jrslod/皿倉登山鉄道/皿倉山ケーブルカー/山上駅", "railname": "皿倉登山鉄道皿倉山ケーブルカー", "door": "NULL"}, "type": "Feature", "geometry": {"type": "Point", "coordinates": [130.79513, 33.84643]}}]}